pysmhi/__init__.py
pysmhi/const.py
pysmhi/exceptions.py
pysmhi/py.typed
pysmhi/smhi.py
pysmhi/smhi_fire_forecast.py
pysmhi/smhi_forecast.py
pysmhi-1.1.0.dist-info/METADATA
pysmhi-1.1.0.dist-info/WHEEL
pysmhi-1.1.0.dist-info/licenses/LICENSE
pysmhi-1.1.0.dist-info/RECORD
