Metadata-Version: 2.4
Name: pysmhi
Version: 1.1.0
Summary: Retrieve open data from SMHI api.
License: MIT
License-File: LICENSE
Keywords: smhi,api,async,client
Author: G Johansson
Author-email: goran.johansson@shiftit.se
Maintainer: G Johansson
Maintainer-email: goran.johansson@shiftit.se
Requires-Python: >=3.11,<4.0
Classifier: Development Status :: 5 - Production/Stable
Classifier: Intended Audience :: Developers
Classifier: License :: OSI Approved :: MIT License
Classifier: Natural Language :: English
Classifier: Programming Language :: Python :: 3
Classifier: Programming Language :: Python :: 3.11
Classifier: Programming Language :: Python :: 3.12
Classifier: Programming Language :: Python :: 3.13
Classifier: Programming Language :: Python :: 3.14
Classifier: Topic :: Software Development :: Libraries :: Python Modules
Requires-Dist: aiohttp (>=3.9.2)
Project-URL: Bug Tracker, https://github.com/gjohansson-ST/pysmhi/issues
Project-URL: Changelog, https://github.com/gjohansson-ST/pysmhi/releases
Project-URL: Documentation, https://github.com/gjohansson-ST/pysmhi
Project-URL: Homepage, https://github.com/gjohansson-ST/pysmhi
Project-URL: Repository, https://github.com/gjohansson-ST/pysmhi
